setup.py
django_featured_item.egg-info/PKG-INFO
django_featured_item.egg-info/SOURCES.txt
django_featured_item.egg-info/dependency_links.txt
django_featured_item.egg-info/requires.txt
django_featured_item.egg-info/top_level.txt
featureditem/__init__.py
featureditem/fields.py
featureditem/models.py
featureditem/tests.py