Metadata-Version: 1.1
Name: django-featured-item
Version: 0.4.1
Summary: Mark a single record in a model as featured
Home-page: https://bitbucket.org/tim_heap/django-featured-item
Author: Tim Heap
Author-email: heap.tim@gmail.com
License: UNKNOWN
Platform: UNKNOWN
Classifier: Environment :: Web Environment
Classifier: Intended Audience :: Developers
Classifier: Operating System :: OS Independent
Classifier: Programming Language :: Python
Classifier: Framework :: Django
